{"cameraMode":{"drawMode":2,"name":"Shaded Wireframe","section":"Shading Mode"},"sceneLighting":false,"audioPlay":false,"sceneViewState":{"m_AlwaysRefresh":false,"showFog":true,"showSkybox":false,"showFlares":true,"showImageEffects":true,"showParticleSystems":true,"showVisualEffectGraphs":true,"m_FxEnabled":true},"in2DMode":false,"pivot":{"x":457.2290954589844,"y":28.490673065185548,"z":169.00555419921876},"rotation":{"x":0.14931584894657136,"y":-0.0400334969162941,"z":0.006050440017133951,"w":0.9879622459411621},"size":1.6622512340545655,"orthographic":false}